ghostscript/__init__.py
ghostscript/_errors.py
ghostscript/_gsprint.py
python3_ghostscript-0.5.0.dist-info/DESCRIPTION.rst
python3_ghostscript-0.5.0.dist-info/METADATA
python3_ghostscript-0.5.0.dist-info/RECORD
python3_ghostscript-0.5.0.dist-info/WHEEL
python3_ghostscript-0.5.0.dist-info/metadata.json
python3_ghostscript-0.5.0.dist-info/top_level.txt
python3_ghostscript-0.5.0.dist-info/zip-safe
