Metadata-Version: 1.1
Name: python3-ghostscript
Version: 0.5.0
Summary: Interface to the Ghostscript C-API, both high- and low-level, based on ctypes
Home-page: http://bitbucket.org/htgoebel/python-ghostscript
Author: Hartmut Goebel (forked by kozea)
Author-email: h.goebel@crazy-compilers.com
License: GPL 3.0
Download-URL: http://pypi.python.org/pypi/ghostscript
Keywords: Ghostscript,PDF,Postscript
Platform: UNKNOWN
Classifier: Development Status :: 4 - Beta
Classifier: Intended Audience :: Developers
Classifier: License :: OSI Approved :: GNU General Public License (GPL)
Classifier: Natural Language :: English
Classifier: Operating System :: OS Independent
Classifier: Programming Language :: Python
Classifier: Programming Language :: Python :: 3.5
Classifier: Topic :: Software Development :: Libraries :: Python Modules
